{
  "people": [
    {
      "name": "Davíð Ásmundsson",
      "nickname": "Davíð",
      "image": [],
      "birthday": "21/01/2002",
      "facts": []
    },
    {
      "name": "Jónas Sturla Sverrisson",
      "nickname": "Jónas",
      "image": [
        "images/people/animal_ai/Jónas.png"
      ],
      "birthday": "24/01/1963",
      "facts": []
    },
    {
      "name": "Sveinbjörn Grétarsson",
      "nickname": "Bjössi",
      "image": [
        "images/people/myndataka/bjossi.jpg",
        "images/people/animal_ai/Bjössi.png"
      ],
      "birthday": "25/01/1967",
      "facts": []
    },
    {
      "name": "Jakob Philip",
      "nickname": "Jakob",
      "image": [
        "images/people/animal_ai/Jakob.png"
      ],
      "birthday": "25/01/1986",
      "facts": []
    },
    {
      "name": "Einar Gunnlaugsson",
      "nickname": "Einar G.",
      "image": [
        "images/people/animal_ai/Einar G.png"
      ],
      "birthday": "29/01/1995",
      "facts": []
    },
    {
      "name": "Sverrir Bergþór Sverrisson",
      "nickname": "Sverrir",
      "image": [
        "images/people/myndataka/sverrir.jpg",
        "images/people/myndataka/sverrir_2.jpg",
        "images/people/animal_ai/Sverrir.png"
      ],
      "birthday": "13/02/1973",
      "facts": []
    },
    {
      "name": "Þórunn Stefánsdóttir",
      "nickname": "Þórunn",
      "image": [
        "images/people/myndataka/thorunn.jpg",
        "images/people/myndataka/thorunn_2.jpg",
        "images/people/animal_ai/Þórunn.png"
      ],
      "birthday": "01/03/1979",
      "facts": []
    },
    {
      "name": "Sigmar Stefánsson",
      "nickname": "Simmi",
      "image": [
        "images/people/myndataka/simmi.jpg",
        "images/people/animal_ai/Simmi.png"
      ],
      "birthday": "02/03/1980",
      "facts": []
    },
    {
      "name": "Roland Nóason",
      "nickname": "Roland",
      "image": [
        "images/people/animal_ai/Róland.png"
      ],
      "birthday": "09/03/1983",
      "facts": []
    },
    {
      "name": "Snorri Vignisson",
      "nickname": "Snorri",
      "image": [
        "images/people/myndataka/snorri.jpg",
        "images/people/animal_ai/Snorri.png"
      ],
      "birthday": "22/04/1997",
      "facts": []
    },
    {
      "name": "Sigurður Másson",
      "nickname": "Siggi",
      "image": [
        "images/people/animal_ai/Siggi.png"
      ],
      "birthday": "28/04/1968",
      "facts": []
    },
    {
      "name": "Haraldur Agnar Bjarnason",
      "nickname": "Halli",
      "image": [
        "images/people/myndataka/halli.jpg",
        "images/people/myndataka/halli_2.jpg",
        "images/people/halli.jpg",
        "images/people/animal_ai/Halli.png"
      ],
      "birthday": "05/05/1975",
      "facts": ["Kom með 2 kökur árið 2026...daginn eftir afmælið"]
    },
    {
      "name": "Kolbrún Klara Gísladóttir",
      "nickname": "Klara",
      "image": [
        "images/people/myndataka/klara.jpg",
        "images/people/animal_ai/Klara.png"
      ],
      "birthday": "10/05/1993",
      "facts": []
    },
    {
      "name": "Björn Þorvarðarson",
      "nickname": "Björn",
      "image": [
        "images/people/animal_ai/Björn.png"
      ],
      "birthday": "10/05/1984",
      "facts": []
    },
    {
      "name": "Zaki Ögmundsson",
      "nickname": "Zaki",
      "image": [
        "images/people/myndataka/zaki.jpg",
        "images/people/animal_ai/Zaki.png"
      ],
      "birthday": "11/05/1986",
      "facts": []
    },
    {
      "name": "Einar Ársæll Hrafnsson",
      "nickname": "Einar Ársæll",
      "image": [
        "images/people/myndataka/einar_a.jpg",
        "images/people/animal_ai/Einar Á.png"
      ],
      "birthday": "15/05/1971",
      "facts": []
    },
    {
      "name": "Óli H. Konráðsson",
      "nickname": "Óli",
      "image": [
        "images/people/myndataka/oli.jpg",
        "images/people/myndataka/oli_2.jpg",
        "images/people/animal_ai/Óli.png"
      ],
      "birthday": "18/05/1977",
      "facts": []
    },
    {
      "name": "Jenný Huyen Andradóttir",
      "nickname": "Jenný",
      "image": [
        "images/people/myndataka/jenny.jpg",
        "images/people/animal_ai/Jenný.png"
      ],
      "birthday": "28/05/1990",
      "facts": []
    },
    {
      "name": "Arnaldur F. Axfjörð",
      "nickname": "Addi",
      "image": [
        "images/people/myndataka/addi.jpg",
        "images/people/animal_ai/Addi.png"
      ],
      "birthday": "18/06/1960",
      "facts": []
    },
    {
      "name": "Ásdís Svava Hallgrímsdóttir",
      "nickname": "Ásdís",
      "image": [
        "images/people/animal_ai/Ásdís.png"
      ],
      "birthday": "27/06/1987",
      "facts": []
    },
    {
      "name": "Sigríður Sveinsdóttir",
      "nickname": "Sigga",
      "image": [
        "images/people/myndataka/sigga.jpg",
        "images/people/animal_ai/Sigga.png"
      ],
      "birthday": "29/06/1991",
      "facts": []
    },
    {
      "name": "Þórir Magnússon",
      "nickname": "Þórir",
      "image": [
        "images/people/myndataka/thorir.jpg",
        "images/people/animal_ai/Þórir.png"
      ],
      "birthday": "08/07/1977",
      "facts": []
    },
    {
      "name": "Kristján Björgvin Schram",
      "nickname": "Kristján",
      "image": [
        "images/people/myndataka/kristjan.jpg",
        "images/people/animal_ai/Kristján.png"
      ],
      "birthday": "23/07/1991",
      "facts": []
    },
    {
      "name": "Írena Rut Jónsdóttir",
      "nickname": "Írena",
      "image": [
        "images/people/myndataka/irena.jpg",
        "images/people/animal_ai/Írena.png"
      ],
      "birthday": "04/08/1998",
      "facts": []
    },
    {
      "name": "Magnea Sigríður Guðmundsdóttir",
      "nickname": "Magnea",
      "image": [
        "images/people/animal_ai/Magnea.png"
      ],
      "birthday": "05/08/1981",
      "facts": []
    },
    {
      "name": "Kristín Lind Steingrímsdóttir",
      "nickname": "Kristín",
      "image": [
        "images/people/myndataka/kristin.jpg",
        "images/people/myndataka/kristin_2.jpg",
        "images/people/animal_ai/Kristín.png"
      ],
      "birthday": "26/08/1975",
      "facts": []
    },
    {
      "name": "Erla Valgerður Birgisdóttir",
      "nickname": "Erla",
      "image": [
        "images/people/myndataka/erla.jpg",
        "images/people/animal_ai/Erla.png"
      ],
      "birthday": "31/08/1994",
      "facts": []
    },
    {
      "name": "Ingibjörg Erna Jónsdóttir",
      "nickname": "Ingibjörg",
      "image": [
        "images/people/myndataka/ingibjorg.jpg",
        "images/people/animal_ai/Ingibjörg.png"
      ],
      "birthday": "24/10/1981",
      "facts": []
    },
    {
      "name": "Erna Birgisdóttir",
      "nickname": "Erna",
      "image": [
        "images/people/myndataka/erna.jpg",
        "images/people/animal_ai/Erna.png"
      ],
      "birthday": "11/11/1986",
      "facts": []
    },
    {
      "name": "Ásmundur Sveinsson",
      "nickname": "Ási",
      "image": [
        "images/people/myndataka/asi.jpg",
        "images/people/animal_ai/Ási.png"
      ],
      "birthday": "22/11/1985",
      "facts": []
    },
    {
      "name": "Tanja Kristín Leifsdóttir",
      "nickname": "Tanja",
      "image": [
        "images/people/myndataka/tanja.jpg",
        "images/people/animal_ai/Tanja.png"
      ],
      "birthday": "27/11/1989",
      "facts": []
    },
    {
      "name": "Vala Kristín Theodórsdóttir",
      "nickname": "Vala",
      "image": [
        "images/people/myndataka/vala.jpg",
        "images/people/myndataka/vala_2.jpg",
        "images/people/animal_ai/Vala.png"
      ],
      "birthday": "14/12/1998",
      "facts": []
    },
    {
      "name": "Elvar Bjarki Böðvarsson",
      "nickname": "Elvar",
      "image": [
        "images/people/myndataka/elvar.jpg",
        "images/people/animal_ai/Elvar.png"
      ],
      "birthday": "18/12/1979",
      "facts": []
    }
  ],
  "events": [
    {
      "title": "Árshátíð Auðkennis",
      "date": "2026-05-15",
      "promo_days_before": 14,
      "graphic": [
        "https://dynamic-media-cdn.tripadvisor.com/media/photo-o/1b/4f/c2/7d/hotel-riu-plaza-berlin.jpg?w=1400&h=800&s=1",
        "https://www.alice-rooftop.de/img/gallery/fullsize/image_225_20220802185438.jpg",
        "https://www.visitberlin.de/system/files/styles/visitberlin_bleed_header_visitberlin_tablet_landscape_2x/private/image/Panorama_Berlin_Mitte_GettyImages-648821756_Getty_Images_Foto_bluejayphoto_web.jpg.webp?itok=R0yktL9O",
        "https://img.static-kl.com/transform/a9eb8d2d-c180-4f6c-877c-3d4a44bbff3f/?io=transform:fill,width:1920&consumerid=bwp",
        "https://berlin-stag-do.com/wp-content/uploads/berlin-beer-bike-scaled.webp",
        "https://www.101bikerentals.com/wp-content/uploads/2018/02/nextbike_bike_rental_berlin.jpg"
      ],
      "description": "",
      "facts": [
        "Berlín er um það bil níu sinnum stærri en París að flatarmáli og Þýskaland á landamæri að flestum ríkjum í Mið-Evrópu, eða alls 9 nágrannalöndum.",
        "Frá 1961 til 1989 var Berlín skipt í tvennt af Berlínarmúrnum. Austur-Berlín var höfuðborg Austur-Þýskalands en Vestur-Berlín var eyja innan Austur-Þýskalands.",
        "Berlínarmúrinn var 155 km að lengd og umkringdi alla Vestur-Berlín. Hann féll 9. nóvember 1989 og er það einn af sögulegustu atburðum 20. aldar.",
        "Í Berlín eru fleiri brýr en í Feneyjum — um 1.700 brýr liggja yfir árnar og skurðina í borginni.",
        "Müggelsee er stærsta lón í Berlín og er vinsæll útivistarstaður.",
        "Berlín er heimsþekkt fyrir listalíf sitt og er með yfir 170 söfn, þar á meðal þrjú sem eru á heimsminjaskrá UNESCO á svokölluðum Múseumseyjum.",
        "Berlín hýsir um 1.000 stóra tónleikaviðburði á ári og er talin ein af stærstu tónlistarborgum heims.",
        "Berlín er ein af heimslegum miðstöðvum tæknitónlistar (techno) og klúbburinn Berghain er einn sá frægasti í heimi.",
        "Um 30% borgarinnar er garðar, skógar eða vatnasvæði — eitt hæsta hlutfall meðal stórborga í Evrópu.",
        "Tiergarten er 3 km² að stærð og var upphaflega konunglegur veiðigarður.",
        "Brandenburg-hliðið var byggt 1791 og er eitt þekktasta kennileiti Þýskalands. Á tíma kalda stríðsins stóð það rétt við múrinn.",
        "Berlín er sú heimsborg þar sem hlutfall hjólreiðamanna er hvað hæst í Evrópu —  með um 500.000 km af hjólreiðastígum.",
        "Berlín er þriðja mest heimsótta borg Evrópu á eftir París og London með yfir 13 milljón gesta á ári.",
        "Zoo Berlin er elsti og arðbærasti dýragarður Þýskalands og býður uppá mesta fjölbreytni dýrategunda í heiminum.",
        "Íbúar Berlín eru um 3,7 milljónir og er borgin stærsta borg Evrópusambandsins.",
        "Eftir að 80% borgarinnar eyðilagðist í seinni heimsstyrjöldinni var stór hluti endurbyggður frá grunni.",
        "Gler hvolfþakið á ríkisþinghúsinu (Reichstags) var hannað af Norman Foster og er einn vinsælasti ferðamannastaðurinn — hægt er að ganga upp í það ókeypis.",
        "Þrátt fyrir að vera höfuðborg stórrar þjóðar er Berlín meðal ódýrustu höfuðborga Vestur-Evrópu — sérstaklega þegar kemur að húsnæðis- og matvörukostnaði."
      ]
    }
  ]
}