{
  "updated": "2026-06-25T08:10:30Z",
  "standings": [
    {
      "rank": 1,
      "name": "Írena",
      "points": 150
    },
    {
      "rank": 2,
      "name": "Vala Stína",
      "points": 142
    },
    {
      "rank": 3,
      "name": "Ásmundur Sveinsson",
      "points": 138
    },
    {
      "rank": 4,
      "name": "Kristján Björgvin Schram",
      "points": 135
    },
    {
      "rank": 5,
      "name": "Erna",
      "points": 133
    },
    {
      "rank": 6,
      "name": "Ásdís Svava Hallgrímsdóttir",
      "points": 130
    },
    {
      "rank": 7,
      "name": "Bjössi",
      "points": 126
    },
    {
      "rank": 7,
      "name": "Þórir",
      "points": 126
    },
    {
      "rank": 9,
      "name": "Erla perla",
      "points": 121
    },
    {
      "rank": 10,
      "name": "Simmi",
      "points": 109
    },
    {
      "rank": 11,
      "name": "Klara",
      "points": 79
    }
  ]
}